Metadata-Version: 2.1
Name: termux
Version: 1.0.0
Summary: A Python based Termux api wrapper
Home-page: https://github.com/AXDZ/termux
Author: Aldas
License: MIT
Platform: UNKNOWN
Classifier: License :: OSI Approved :: MIT License
Classifier: Programming Language :: Python :: 3
Classifier: Programming Language :: Python :: 3.7
